{"GlobalPropertiesHash":"cjqwCucQJEzE0ECQufClZVIiQpOAWoU5RY40wYKeU2M=","FingerprintPatternsHash":"gq3WsqcKBUGTSNle7RKKyXRIwh7M8ccEqOqYvIzoM04=","PropertyOverridesHash":"8ZRc1sGeVrPBx4lD717BgRaQekyh78QKV9SKsdt638U=","InputHashes":["rWl5geHMEo0IA/dxri2RWcDlveoHrlVQVAfomV3smMU=","pLc9tKDm6f54CyfhQa0wOfo4EVns7j1Yr7PVFA5C3Ug=","aQCWauE1s0WqDb30k04mcAF5mev7tArWz7otTGW628w=","6JqHUsJV4cQQO81f2FrH\u002BO546EmzYMN6e\u002ByaISfEGAc=","418b2dDe1ZWIP3Tz\u002Bh9uBRD2wu51rDtf9pTYB6zxvBY=","Hcx\u002Bo6y5BRbN1lGKRfgjGNe9PbkvYQXipnClyd5UGfU=","YJH6i3oa4A5yCuNvRobg3Frs2ggics7wCAUpaR9EzHc=","VbWQkeR05GL0XnJHoJx8KYpa6JFHzc7/8dRKb/q0NnU=","AUeBHAVBLCSon\u002B7qtoxsyQPqNdYAWyOD7sCggvzgWJI=","PP18bf6KBx0p6aqLz9f0f3/0Yua3RQNI/N8e4ZqZnLY=","Y7NQTXH50QE9baDPjm\u002Bpt1gwV1AVnRaHc17MdSTcSyk=","hV3Ye5VZw46MzKg2kgcdl9sQGeF1Bj9xIY7Nd7ZMMV8=","o5LLYiqMBYdEriSlQdApYIH2KGKbJju9pnbI6pFXWw0=","L1yDR3Xc60C5CREadKpPbj/Ovk55oN/X7UIwdAsvTjs=","\u002BgjavyGmIjdcYt9tMRcs9JeJ9OSc0uQpw4AZskzb558=","HMI6Rrfusq4FYKN/u7r8YD7ceudXpfee5RsD6Jn2beY=","II2FWNy8Q4lBzuudMdZCg0v9hQ5Xc8nFTBOF\u002BZ67hiA=","q0mjdyUxw9bZTQS6YoDmwX9Ngqdr2WFOoWWxVk3pBtk=","3Mtc15MOuPkWalpodWwMKpMSiVa0epPmICuvfSvzyVI=","kiNgxFhuARVym5J5qEyBO\u002BFUZlAKfKX1CvmruhnhXdU=","0sjWNbA4/fH0PgI9Wzrm9RvKtwYODRTm5Qe91X17GmY=","s7tyB/6v7s8veG2r/IU/RAAdJ4tax6YuIppZEtpyVns=","NgCQhKOG4yxbmR3tEv78rmLEGSR5isFbQOvzpLAmYyg=","j9PfAUVCwclHVcPT3qk6PngF0KPDNSgAt1hVzaJZmyU=","9L\u002BGLmcs/sH5r5zDGWySivLJ2WkXNN2z\u002B9ki3abLkg0=","wMMFRVp3BABssBzP/Dmc2sFA4MQwevMVMCzGiHVwoD8=","8D1nDmEHnwwVpvWIhDnSKG6aRg747\u002BG/B0y5A6aBY9c="],"CachedAssets":{"rWl5geHMEo0IA/dxri2RWcDlveoHrlVQVAfomV3smMU=":{"Identity":"C:\\Users\\benja\\source\\Anti\\SmileRadio\\SmileRadio.Client\\wwwroot\\css\\bootstrap\\bootstrap.min.css","SourceId":"SmileRadio.Client","SourceType":"Discovered","ContentRoot":"C:\\Users\\benja\\source\\Anti\\SmileRadio\\SmileRadio.Client\\wwwroot\\","BasePath":"/","RelativePath":"css/bootstrap/bootstrap.min#[.{fingerprint}]?.css","AssetKind":"All","AssetMode":"All","AssetRole":"Primary","AssetMergeBehavior":null,"AssetMergeSource":"","RelatedAsset":null,"AssetTraitName":null,"AssetTraitValue":null,"Fingerprint":"bpk8xqwxhs","Integrity":"z8OR40MowJ8GgK6P89Y\u002BhiJK5\u002BcclzFHzLhFQLL92bg=","CopyToOutputDirectory":"Never","CopyToPublishDirectory":"PreserveNewest","OriginalItemSpec":"wwwroot\\css\\bootstrap\\bootstrap.min.css","FileLength":162720,"LastWriteTime":"2026-02-17T16:10:07.7280126+00:00"},"pLc9tKDm6f54CyfhQa0wOfo4EVns7j1Yr7PVFA5C3Ug=":{"Identity":"C:\\Users\\benja\\source\\Anti\\SmileRadio\\SmileRadio.Client\\wwwroot\\css\\bootstrap\\bootstrap.min.css.map","SourceId":"SmileRadio.Client","SourceType":"Discovered","ContentRoot":"C:\\Users\\benja\\source\\Anti\\SmileRadio\\SmileRadio.Client\\wwwroot\\","BasePath":"/","RelativePath":"css/bootstrap/bootstrap.min.css#[.{fingerprint}]?.map","AssetKind":"All","AssetMode":"All","AssetRole":"Primary","AssetMergeBehavior":null,"AssetMergeSource":"","RelatedAsset":null,"AssetTraitName":null,"AssetTraitValue":null,"Fingerprint":"8inm30yfxf","Integrity":"gBwg2tmA0Ci2u54gMF1jNCVku6vznarkLS6D76htNNQ=","CopyToOutputDirectory":"Never","CopyToPublishDirectory":"PreserveNewest","OriginalItemSpec":"wwwroot\\css\\bootstrap\\bootstrap.min.css.map","FileLength":449111,"LastWriteTime":"2026-02-17T16:10:07.7305637+00:00"},"aQCWauE1s0WqDb30k04mcAF5mev7tArWz7otTGW628w=":{"Identity":"C:\\Users\\benja\\source\\Anti\\SmileRadio\\SmileRadio.Client\\wwwroot\\css\\open-iconic\\FONT-LICENSE","SourceId":"SmileRadio.Client","SourceType":"Discovered","ContentRoot":"C:\\Users\\benja\\source\\Anti\\SmileRadio\\SmileRadio.Client\\wwwroot\\","BasePath":"/","RelativePath":"css/open-iconic/FONT-LICENSE#[.{fingerprint}]?","AssetKind":"All","AssetMode":"All","AssetRole":"Primary","AssetMergeBehavior":null,"AssetMergeSource":"","RelatedAsset":null,"AssetTraitName":null,"AssetTraitValue":null,"Fingerprint":"48tmkg660f","Integrity":"jA4J4h/k76zVxbFKEaWwFKJccmO0voOQ1DbUW\u002B5YNlI=","CopyToOutputDirectory":"Never","CopyToPublishDirectory":"PreserveNewest","OriginalItemSpec":"wwwroot\\css\\open-iconic\\FONT-LICENSE","FileLength":4103,"LastWriteTime":"2026-02-17T16:10:07.7305637+00:00"},"6JqHUsJV4cQQO81f2FrH\u002BO546EmzYMN6e\u002ByaISfEGAc=":{"Identity":"C:\\Users\\benja\\source\\Anti\\SmileRadio\\SmileRadio.Client\\wwwroot\\css\\open-iconic\\font\\css\\open-iconic-bootstrap.min.css","SourceId":"SmileRadio.Client","SourceType":"Discovered","ContentRoot":"C:\\Users\\benja\\source\\Anti\\SmileRadio\\SmileRadio.Client\\wwwroot\\","BasePath":"/","RelativePath":"css/open-iconic/font/css/open-iconic-bootstrap.min#[.{fingerprint}]?.css","AssetKind":"All","AssetMode":"All","AssetRole":"Primary","AssetMergeBehavior":null,"AssetMergeSource":"","RelatedAsset":null,"AssetTraitName":null,"AssetTraitValue":null,"Fingerprint":"cmapd0fi15","Integrity":"BJ/G\u002Be\u002By7bQdrYkS2RBTyNfBHpA9IuGaPmf9htub5MQ=","CopyToOutputDirectory":"Never","CopyToPublishDirectory":"PreserveNewest","OriginalItemSpec":"wwwroot\\css\\open-iconic\\font\\css\\open-iconic-bootstrap.min.css","FileLength":9395,"LastWriteTime":"2026-02-17T16:10:07.673655+00:00"},"418b2dDe1ZWIP3Tz\u002Bh9uBRD2wu51rDtf9pTYB6zxvBY=":{"Identity":"C:\\Users\\benja\\source\\Anti\\SmileRadio\\SmileRadio.Client\\wwwroot\\css\\open-iconic\\font\\fonts\\open-iconic.eot","SourceId":"SmileRadio.Client","SourceType":"Discovered","ContentRoot":"C:\\Users\\benja\\source\\Anti\\SmileRadio\\SmileRadio.Client\\wwwroot\\","BasePath":"/","RelativePath":"css/open-iconic/font/fonts/open-iconic#[.{fingerprint}]?.eot","AssetKind":"All","AssetMode":"All","AssetRole":"Primary","AssetMergeBehavior":null,"AssetMergeSource":"","RelatedAsset":null,"AssetTraitName":null,"AssetTraitValue":null,"Fingerprint":"0uw8dim9nl","Integrity":"OK3poGPgzKI2NzNgP07XMbJa3Dz6USoUh/chSkSvQpc=","CopyToOutputDirectory":"Never","CopyToPublishDirectory":"PreserveNewest","OriginalItemSpec":"wwwroot\\css\\open-iconic\\font\\fonts\\open-iconic.eot","FileLength":28196,"LastWriteTime":"2026-02-17T16:10:07.6746505+00:00"},"Hcx\u002Bo6y5BRbN1lGKRfgjGNe9PbkvYQXipnClyd5UGfU=":{"Identity":"C:\\Users\\benja\\source\\Anti\\SmileRadio\\SmileRadio.Client\\wwwroot\\css\\open-iconic\\font\\fonts\\open-iconic.otf","SourceId":"SmileRadio.Client","SourceType":"Discovered","ContentRoot":"C:\\Users\\benja\\source\\Anti\\SmileRadio\\SmileRadio.Client\\wwwroot\\","BasePath":"/","RelativePath":"css/open-iconic/font/fonts/open-iconic#[.{fingerprint}]?.otf","AssetKind":"All","AssetMode":"All","AssetRole":"Primary","AssetMergeBehavior":null,"AssetMergeSource":"","RelatedAsset":null,"AssetTraitName":null,"AssetTraitValue":null,"Fingerprint":"wk8x8xm0ah","Integrity":"sDUtuZAEzWZyv/U1xl/9D3ehyU69JE\u002BFvAcu5HQ\u002B/a0=","CopyToOutputDirectory":"Never","CopyToPublishDirectory":"PreserveNewest","OriginalItemSpec":"wwwroot\\css\\open-iconic\\font\\fonts\\open-iconic.otf","FileLength":20996,"LastWriteTime":"2026-02-17T16:10:07.6767097+00:00"},"YJH6i3oa4A5yCuNvRobg3Frs2ggics7wCAUpaR9EzHc=":{"Identity":"C:\\Users\\benja\\source\\Anti\\SmileRadio\\SmileRadio.Client\\wwwroot\\css\\open-iconic\\font\\fonts\\open-iconic.svg","SourceId":"SmileRadio.Client","SourceType":"Discovered","ContentRoot":"C:\\Users\\benja\\source\\Anti\\SmileRadio\\SmileRadio.Client\\wwwroot\\","BasePath":"/","RelativePath":"css/open-iconic/font/fonts/open-iconic#[.{fingerprint}]?.svg","AssetKind":"All","AssetMode":"All","AssetRole":"Primary","AssetMergeBehavior":null,"AssetMergeSource":"","RelatedAsset":null,"AssetTraitName":null,"AssetTraitValue":null,"Fingerprint":"sjnzgf7e1h","Integrity":"\u002BP1oQ5jPzOVJGC52E1oxGXIXxxCyMlqy6A9cNxGYzVk=","CopyToOutputDirectory":"Never","CopyToPublishDirectory":"PreserveNewest","OriginalItemSpec":"wwwroot\\css\\open-iconic\\font\\fonts\\open-iconic.svg","FileLength":55332,"LastWriteTime":"2026-02-17T16:10:07.6767097+00:00"},"VbWQkeR05GL0XnJHoJx8KYpa6JFHzc7/8dRKb/q0NnU=":{"Identity":"C:\\Users\\benja\\source\\Anti\\SmileRadio\\SmileRadio.Client\\wwwroot\\css\\open-iconic\\font\\fonts\\open-iconic.ttf","SourceId":"SmileRadio.Client","SourceType":"Discovered","ContentRoot":"C:\\Users\\benja\\source\\Anti\\SmileRadio\\SmileRadio.Client\\wwwroot\\","BasePath":"/","RelativePath":"css/open-iconic/font/fonts/open-iconic#[.{fingerprint}]?.ttf","AssetKind":"All","AssetMode":"All","AssetRole":"Primary","AssetMergeBehavior":null,"AssetMergeSource":"","RelatedAsset":null,"AssetTraitName":null,"AssetTraitValue":null,"Fingerprint":"ll5grcv8wv","Integrity":"p\u002BRP8CV3vRK1YbIkNzq3rPo1jyETPnR07ULb\u002BHVYL8w=","CopyToOutputDirectory":"Never","CopyToPublishDirectory":"PreserveNewest","OriginalItemSpec":"wwwroot\\css\\open-iconic\\font\\fonts\\open-iconic.ttf","FileLength":28028,"LastWriteTime":"2026-02-17T16:10:07.6777173+00:00"},"AUeBHAVBLCSon\u002B7qtoxsyQPqNdYAWyOD7sCggvzgWJI=":{"Identity":"C:\\Users\\benja\\source\\Anti\\SmileRadio\\SmileRadio.Client\\wwwroot\\css\\open-iconic\\font\\fonts\\open-iconic.woff","SourceId":"SmileRadio.Client","SourceType":"Discovered","ContentRoot":"C:\\Users\\benja\\source\\Anti\\SmileRadio\\SmileRadio.Client\\wwwroot\\","BasePath":"/","RelativePath":"css/open-iconic/font/fonts/open-iconic#[.{fingerprint}]?.woff","AssetKind":"All","AssetMode":"All","AssetRole":"Primary","AssetMergeBehavior":null,"AssetMergeSource":"","RelatedAsset":null,"AssetTraitName":null,"AssetTraitValue":null,"Fingerprint":"h4d0pazwgy","Integrity":"cZPqVlRJfSNW0KaQ4\u002BUPOXZ/v/QzXlejRDwUNdZIofI=","CopyToOutputDirectory":"Never","CopyToPublishDirectory":"PreserveNewest","OriginalItemSpec":"wwwroot\\css\\open-iconic\\font\\fonts\\open-iconic.woff","FileLength":14984,"LastWriteTime":"2026-02-17T16:10:07.6782844+00:00"},"PP18bf6KBx0p6aqLz9f0f3/0Yua3RQNI/N8e4ZqZnLY=":{"Identity":"C:\\Users\\benja\\source\\Anti\\SmileRadio\\SmileRadio.Client\\wwwroot\\css\\open-iconic\\ICON-LICENSE","SourceId":"SmileRadio.Client","SourceType":"Discovered","ContentRoot":"C:\\Users\\benja\\source\\Anti\\SmileRadio\\SmileRadio.Client\\wwwroot\\","BasePath":"/","RelativePath":"css/open-iconic/ICON-LICENSE#[.{fingerprint}]?","AssetKind":"All","AssetMode":"All","AssetRole":"Primary","AssetMergeBehavior":null,"AssetMergeSource":"","RelatedAsset":null,"AssetTraitName":null,"AssetTraitValue":null,"Fingerprint":"4dwjve0o0b","Integrity":"aF5g/izareSj02F3MPSoTGNbcMBl9nmZKDe04zjU/ss=","CopyToOutputDirectory":"Never","CopyToPublishDirectory":"PreserveNewest","OriginalItemSpec":"wwwroot\\css\\open-iconic\\ICON-LICENSE","FileLength":1093,"LastWriteTime":"2026-02-17T16:10:07.7305637+00:00"},"Y7NQTXH50QE9baDPjm\u002Bpt1gwV1AVnRaHc17MdSTcSyk=":{"Identity":"C:\\Users\\benja\\source\\Anti\\SmileRadio\\SmileRadio.Client\\wwwroot\\css\\open-iconic\\README.md","SourceId":"SmileRadio.Client","SourceType":"Discovered","ContentRoot":"C:\\Users\\benja\\source\\Anti\\SmileRadio\\SmileRadio.Client\\wwwroot\\","BasePath":"/","RelativePath":"css/open-iconic/README#[.{fingerprint}]?.md","AssetKind":"All","AssetMode":"All","AssetRole":"Primary","AssetMergeBehavior":null,"AssetMergeSource":"","RelatedAsset":null,"AssetTraitName":null,"AssetTraitValue":null,"Fingerprint":"5bzwdl5l6x","Integrity":"waukoLqsiIAw/nXpsKkTHnhImmcPijcBEd2lzqzJNN0=","CopyToOutputDirectory":"Never","CopyToPublishDirectory":"PreserveNewest","OriginalItemSpec":"wwwroot\\css\\open-iconic\\README.md","FileLength":3655,"LastWriteTime":"2026-02-17T16:10:07.732015+00:00"},"hV3Ye5VZw46MzKg2kgcdl9sQGeF1Bj9xIY7Nd7ZMMV8=":{"Identity":"C:\\Users\\benja\\source\\Anti\\SmileRadio\\SmileRadio.Client\\wwwroot\\css\\site.css","SourceId":"SmileRadio.Client","SourceType":"Discovered","ContentRoot":"C:\\Users\\benja\\source\\Anti\\SmileRadio\\SmileRadio.Client\\wwwroot\\","BasePath":"/","RelativePath":"css/site#[.{fingerprint}]?.css","AssetKind":"All","AssetMode":"All","AssetRole":"Primary","AssetMergeBehavior":null,"AssetMergeSource":"","RelatedAsset":null,"AssetTraitName":null,"AssetTraitValue":null,"Fingerprint":"zh9s866nx2","Integrity":"Fx\u002Bc1youNLgejKLBM3S2fD6fcDOSv/D7tNQKm5gws6U=","CopyToOutputDirectory":"Never","CopyToPublishDirectory":"PreserveNewest","OriginalItemSpec":"wwwroot\\css\\site.css","FileLength":2978,"LastWriteTime":"2026-02-17T16:10:07.6726513+00:00"},"o5LLYiqMBYdEriSlQdApYIH2KGKbJju9pnbI6pFXWw0=":{"Identity":"C:\\Users\\benja\\source\\Anti\\SmileRadio\\SmileRadio.Client\\wwwroot\\favicon.png","SourceId":"SmileRadio.Client","SourceType":"Discovered","ContentRoot":"C:\\Users\\benja\\source\\Anti\\SmileRadio\\SmileRadio.Client\\wwwroot\\","BasePath":"/","RelativePath":"favicon#[.{fingerprint}]?.png","AssetKind":"All","AssetMode":"All","AssetRole":"Primary","AssetMergeBehavior":null,"AssetMergeSource":"","RelatedAsset":null,"AssetTraitName":null,"AssetTraitValue":null,"Fingerprint":"ifv42okdf2","Integrity":"4mWsDy3aHl36ZbGt8zByK7Pvd4kRUoNgTYzRnwmPHwg=","CopyToOutputDirectory":"Never","CopyToPublishDirectory":"PreserveNewest","OriginalItemSpec":"wwwroot\\favicon.png","FileLength":1148,"LastWriteTime":"2026-02-17T16:10:07.7262706+00:00"},"L1yDR3Xc60C5CREadKpPbj/Ovk55oN/X7UIwdAsvTjs=":{"Identity":"C:\\Users\\benja\\source\\Anti\\SmileRadio\\SmileRadio.Client\\wwwroot\\js\\player.js","SourceId":"SmileRadio.Client","SourceType":"Discovered","ContentRoot":"C:\\Users\\benja\\source\\Anti\\SmileRadio\\SmileRadio.Client\\wwwroot\\","BasePath":"/","RelativePath":"js/player#[.{fingerprint}]?.js","AssetKind":"All","AssetMode":"All","AssetRole":"Primary","AssetMergeBehavior":null,"AssetMergeSource":"","RelatedAsset":null,"AssetTraitName":null,"AssetTraitValue":null,"Fingerprint":"fi923cvbb4","Integrity":"WSAnGRTszGPKxDRH518lB6pSJ1WqaeK7pVYMyTnwHhQ=","CopyToOutputDirectory":"Never","CopyToPublishDirectory":"PreserveNewest","OriginalItemSpec":"wwwroot\\js\\player.js","FileLength":3503,"LastWriteTime":"2026-02-17T16:12:00.8547832+00:00"}},"CachedCopyCandidates":{}}